<?xml version="1.0" encoding="utf-8" ?>
<dwsync>
<file name="db.php" server="107.170.186.55//var/www/unicach/" local="131147527960000000" remote="131147527960000000" Dst="2" />
<file name="cnx.php" server="107.170.186.55//var/www/unicach/" local="131147527960000000" remote="131147527960000000" Dst="2" />
<file name="config.php" server="107.170.186.55//var/www/unicach/" local="131147527960000000" remote="131147527960000000" Dst="2" />
<file name="salon.php" server="107.170.186.55//var/www/unicach/" local="131147527970000000" remote="131147527970000000" Dst="2" />
<file name="usuario.php" server="107.170.186.55//var/www/unicach/" local="131150093196460972" remote="131150112880000000" Dst="2" />
<file name="acceso.php" server="107.170.186.55//var/www/unicach/" local="131148848662399867" remote="131150112880000000" Dst="2" />
<file name=".DS_Store" server="107.170.186.55//var/www/unicach/" local="131147527950000000" remote="131147527950000000" Dst="2" />
<file name="permiso.php" server="107.170.186.55//var/www/unicach/" local="131151172700000000" remote="131151172700000000" Dst="2" />
<file name="grupo.php" server="107.170.186.55//var/www/unicach/" local="131151585125644364" remote="131152639210000000" Dst="2" />
<file name="ciclo.php" server="107.170.186.55//var/www/unicach/" local="131153797560000000" remote="131153797560000000" Dst="2" />
<file name="cliente.php" server="107.170.186.55//var/www/unicach/" local="131147527960000000" remote="131147527960000000" Dst="2" />
<file name="ingreso.php" server="107.170.186.55//var/www/unicach/" local="131147527970000000" remote="131147527970000000" Dst="2" />
<file name="ingresomov.php" server="107.170.186.55//var/www/unicach/" local="131147527970000000" remote="131147527970000000" Dst="2" />
<file name="tipooperacion.php" server="107.170.186.55//var/www/unicach/" local="131147527970000000" remote="131147527970000000" Dst="2" />
</dwsync>